NiukeXinpianShejiYanzhengGongchengshiQiuzhiJingyanFenxiang20212022Fix1/README.md
NiukeXinpianShejiYanzhengGongchengshiQiuzhiJingyanFenxiang20212022Fix1/__init__.py
NiukeXinpianShejiYanzhengGongchengshiQiuzhiJingyanFenxiang20212022Fix1/__main__.py
NiukeXinpianShejiYanzhengGongchengshiQiuzhiJingyanFenxiang20212022Fix1/file.epub
NiukeXinpianShejiYanzhengGongchengshiQiuzhiJingyanFenxiang20212022Fix1/index.html
NiukeXinpianShejiYanzhengGongchengshiQiuzhiJingyanFenxiang20212022Fix1/css/__init__.py
NiukeXinpianShejiYanzhengGongchengshiQiuzhiJingyanFenxiang20212022Fix1/css/annotations.css
NiukeXinpianShejiYanzhengGongchengshiQiuzhiJingyanFenxiang20212022Fix1/css/main.css
NiukeXinpianShejiYanzhengGongchengshiQiuzhiJingyanFenxiang20212022Fix1/css/normalize.css
NiukeXinpianShejiYanzhengGongchengshiQiuzhiJingyanFenxiang20212022Fix1/css/popup.css
NiukeXinpianShejiYanzhengGongchengshiQiuzhiJingyanFenxiang20212022Fix1/font/__init__.py
NiukeXinpianShejiYanzhengGongchengshiQiuzhiJingyanFenxiang20212022Fix1/font/fontello.eot
NiukeXinpianShejiYanzhengGongchengshiQiuzhiJingyanFenxiang20212022Fix1/font/fontello.svg
NiukeXinpianShejiYanzhengGongchengshiQiuzhiJingyanFenxiang20212022Fix1/font/fontello.ttf
NiukeXinpianShejiYanzhengGongchengshiQiuzhiJingyanFenxiang20212022Fix1/font/fontello.woff
NiukeXinpianShejiYanzhengGongchengshiQiuzhiJingyanFenxiang20212022Fix1/img/__init__.py
NiukeXinpianShejiYanzhengGongchengshiQiuzhiJingyanFenxiang20212022Fix1/img/annotator-glyph-sprite.png
NiukeXinpianShejiYanzhengGongchengshiQiuzhiJingyanFenxiang20212022Fix1/img/annotator-icon-sprite.png
NiukeXinpianShejiYanzhengGongchengshiQiuzhiJingyanFenxiang20212022Fix1/img/apple-touch-icon.png
NiukeXinpianShejiYanzhengGongchengshiQiuzhiJingyanFenxiang20212022Fix1/img/cancelfullscreen.png
NiukeXinpianShejiYanzhengGongchengshiQiuzhiJingyanFenxiang20212022Fix1/img/close.png
NiukeXinpianShejiYanzhengGongchengshiQiuzhiJingyanFenxiang20212022Fix1/img/fullscreen.png
niuke_xinpian_sheji_yanzheng_gongchengshi_qiuzhi_jingyan_fenxiang_2021_2022_fix1-2025.3.25.1.dist-info/METADATA
niuke_xinpian_sheji_yanzheng_gongchengshi_qiuzhi_jingyan_fenxiang_2021_2022_fix1-2025.3.25.1.dist-info/WHEEL
niuke_xinpian_sheji_yanzheng_gongchengshi_qiuzhi_jingyan_fenxiang_2021_2022_fix1-2025.3.25.1.dist-info/entry_points.txt
niuke_xinpian_sheji_yanzheng_gongchengshi_qiuzhi_jingyan_fenxiang_2021_2022_fix1-2025.3.25.1.dist-info/top_level.txt
niuke_xinpian_sheji_yanzheng_gongchengshi_qiuzhi_jingyan_fenxiang_2021_2022_fix1-2025.3.25.1.dist-info/RECORD
